README.txt
setup.cfg
setup.py
nfg/__init__.py
nfg.ratedreactions.egg-info/PKG-INFO
nfg.ratedreactions.egg-info/SOURCES.txt
nfg.ratedreactions.egg-info/dependency_links.txt
nfg.ratedreactions.egg-info/entry_points.txt
nfg.ratedreactions.egg-info/not-zip-safe
nfg.ratedreactions.egg-info/requires.txt
nfg.ratedreactions.egg-info/top_level.txt
nfg/ratedreactions/__init__.py
nfg/ratedreactions/db.py
nfg/ratedreactions/enabler.py
nfg/ratedreactions/interfaces.py
nfg/ratedreactions/tests.py
nfg/ratedreactions/browser/__init__.py
nfg/ratedreactions/browser/dbsettings.py
nfg/ratedreactions/browser/interfaces.py
nfg/ratedreactions/browser/viewlets.py