Metadata-Version: 1.0
Name: nfg.ratedreactions
Version: 1.0dev
Summary: A zope3 product to add rated reactions to (plone) content
Home-page: http://www.nfg.nl
Author: NFG Net Facilities Group BV
Author-email: support@nfg.nl
License: GPL
Keywords: plone ratings
Platform: UNKNOWN
Classifier: Framework :: Plone
Classifier: Programming Language :: Python
Classifier: Topic :: Software Development :: Libraries :: Python Modules
